fastpermute/__init__.py
fastpermute/main.py
fastpermute-0.1.0.dist-info/LICENSE
fastpermute-0.1.0.dist-info/METADATA
fastpermute-0.1.0.dist-info/WHEEL
fastpermute-0.1.0.dist-info/top_level.txt
fastpermute-0.1.0.dist-info/RECORD
