Metadata-Version: 2.1
Name: fastpermute
Version: 0.1.0
Summary: Swiftly generate the nth term of permutation sequences.
Home-page: https://github.com/pypa/sampleproject
Author: Artem Lukin
Author-email: artem.d.lukin@gmail.com
License: UNKNOWN
Project-URL: Bug Tracker, https://github.com/pypa/sampleproject/issues
Platform: UNKNOWN
Classifier: Programming Language :: Python :: 3
Classifier: License :: OSI Approved :: MIT License
Classifier: Operating System :: OS Independent
Requires-Python: >=3.6
License-File: LICENSE
